xun/.gitignore
xun/__init__.py
xun/__main__.py
xun/cli.py
xun/core.py
xun/memoized.py
xun/version.py
xun/fs/__init__.py
xun/fs/queries/__init__.py
xun/fs/queries/grammar.py
xun/fs/queries/queries.py
xun/functions/__init__.py
xun/functions/blueprint.py
xun/functions/cli.py
xun/functions/errors.py
xun/functions/function.py
xun/functions/function_description.py
xun/functions/function_image.py
xun/functions/graph.py
xun/functions/runtime.py
xun/functions/transformations.py
xun/functions/util.py
xun/functions/compatibility/__init__.py
xun/functions/compatibility/ast.py
xun/functions/driver/__init__.py
xun/functions/driver/dask.py
xun/functions/driver/driver.py
xun/functions/driver/sequential.py
xun/functions/store/__init__.py
xun/functions/store/disk.py
xun/functions/store/memory.py
xun/functions/store/redis.py
xun/functions/store/sftp.py
xun/functions/store/store.py
xun/functions/store/store_accessor.py
xun/infrastructure/__init__.py
xun/infrastructure/cli.py
xun/infrastructure/crypto.py
xun/init/__init__.py
xun/init/cli.py
xun/init/init_notebook.py
xun/init/cookiecutter-workflow/cookiecutter.json
xun/init/cookiecutter-workflow/hooks/post_gen_project.py
xun/init/cookiecutter-workflow/hooks/pre_gen_project.py
xun/init/cookiecutter-workflow/{{cookiecutter.module_name}}/__init__.py
xun/init/cookiecutter-workflow/{{cookiecutter.module_name}}/__main__.py
xun/init/cookiecutter-workflow/{{cookiecutter.module_name}}/{{cookiecutter.module_name}}.py
xun/serialization/__init__.py
xun/serialization/functor.py
xun/serialization/numpy_types.py
xun/serialization/pandas_types.py
xun/serialization/python_types.py
xun/serialization/xun_types.py
xun/serialization/yaml.py
xun/tests/__init__.py
xun/tests/helpers.py
xun/tests/test_compatibility.py
xun/tests/test_crypto.py
xun/tests/test_drivers.py
xun/tests/test_functions.py
xun/tests/test_functions_cli.py
xun/tests/test_graph.py
xun/tests/test_query_language.py
xun/tests/test_resources.py
xun/tests/test_serialization.py
xun-1.0.0.dist-info/LICENSE
xun-1.0.0.dist-info/METADATA
xun-1.0.0.dist-info/WHEEL
xun-1.0.0.dist-info/entry_points.txt
xun-1.0.0.dist-info/top_level.txt
xun-1.0.0.dist-info/RECORD
