Metadata-Version: 2.1
Name: xun
Version: 1.0.0
Summary: xun: package generated with cookiecutter-equinor
Home-page: https://github.com/equinor/xun
Author: Equinor
Author-email: jegm@equinor.com
License: GNU General Public License v3
Project-URL: Documentation, https://xun.readthedocs.io/
Project-URL: Issue Tracker, https://github.com/equinor/xun/issues
Platform: any
Requires-Python: >=3
License-File: LICENSE
Requires-Dist: astor
Requires-Dist: cookiecutter
Requires-Dist: cryptography
Requires-Dist: dask[distributed]
Requires-Dist: immutables
Requires-Dist: matplotlib
Requires-Dist: nbformat
Requires-Dist: networkx
Requires-Dist: numpy
Requires-Dist: pandas
Requires-Dist: paramiko
Requires-Dist: redis
Requires-Dist: yapf
